{
  "category": "Uncategorized",
  "description": "Resolve all defects found in the Deep Audit v2 for `hx-contextual-help`.\nSource: `packages/hx-library/src/components/hx-contextual-help/AUDIT.md`\n\n**Summary:** 13 defects — 1 P0, 5 P1, 7 P2, 0 P3\n\n### P0 — Critical\n- [ ] [P0] 01: `role=\"dialog\"` without accessible name when `heading` is empty\n\nReference the AUDIT.md in the component directory for full details and code locations.",
  "title": "Audit Fix: hx-contextual-help",
  "status": "backlog",
  "complexity": "medium",
  "priority": 3,
  "source": "api",
  "trustTier": 1,
  "quarantineStatus": "passed",
  "quarantineId": "fee2149d-3ce9-4aeb-9a4a-ecb128b72b81",
  "id": "feature-1772853667582-4jvtosyii",
  "branchName": "feature/audit-fix-hx-contextual-help",
  "descriptionHistory": [
    {
      "description": "Resolve all defects found in the Deep Audit v2 for `hx-contextual-help`.\nSource: `packages/hx-library/src/components/hx-contextual-help/AUDIT.md`\n\n**Summary:** 13 defects — 1 P0, 5 P1, 7 P2, 0 P3\n\n### P0 — Critical\n- [ ] [P0] 01: `role=\"dialog\"` without accessible name when `heading` is empty\n\nReference the AUDIT.md in the component directory for full details and code locations.",
      "timestamp": "2026-03-07T03:21:07.582Z",
      "source": "initial"
    }
  ],
  "createdAt": "2026-03-07T03:21:07.582Z",
  "statusHistory": [
    {
      "from": null,
      "to": "backlog",
      "timestamp": "2026-03-07T03:21:07.582Z",
      "reason": "Feature created"
    }
  ]
}