{
  "category": "Uncategorized",
  "description": "Launch readiness audit for hx-toast. Checklist: (1) A11y — axe-core zero violations, alert/status role, live region, auto-dismiss timing (WCAG 2.2.1), WCAG 2.1 AA. (2) Astro doc page — all 12 template sections. (3) Individual export — standalone HTML works. (4) `npm run verify` passes. Files: `packages/hx-library/src/components/hx-toast/`, `apps/docs/src/content/docs/component-library/hx-toast.md`",
  "title": "LAUNCH READY: hx-toast",
  "status": "backlog",
  "dependencies": [
    "feature-1773066138511-g2pgj0rmm"
  ],
  "complexity": "medium",
  "priority": 3,
  "source": "api",
  "trustTier": 1,
  "quarantineStatus": "passed",
  "quarantineId": "20ea4378-c835-4b24-86b7-9270eeea11ea",
  "id": "feature-1773066421672-nhybw3mtq",
  "branchName": "feature/launch-ready-hx-toast",
  "descriptionHistory": [
    {
      "description": "Launch readiness audit for hx-toast. Checklist: (1) A11y — axe-core zero violations, alert/status role, live region, auto-dismiss timing (WCAG 2.2.1), WCAG 2.1 AA. (2) Astro doc page — all 12 template sections. (3) Individual export — standalone HTML works. (4) `npm run verify` passes. Files: `packages/hx-library/src/components/hx-toast/`, `apps/docs/src/content/docs/component-library/hx-toast.md`",
      "timestamp": "2026-03-09T14:27:01.672Z",
      "source": "initial"
    }
  ],
  "createdAt": "2026-03-09T14:27:01.672Z",
  "statusHistory": [
    {
      "from": null,
      "to": "backlog",
      "timestamp": "2026-03-09T14:27:01.672Z",
      "reason": "Feature created"
    }
  ]
}