{
  "category": "Uncategorized",
  "description": "## Deep Component Audit — hx-accordion\n\n**Component directory:** `packages/hx-library/src/components/hx-accordion/`\n**Sub-components:** hx-accordion-item (lives in same directory)\n\n### Audit Scope (ALL areas — leave nothing unchecked)\n\n1. **Design Tokens** — Verify ALL CSS custom properties use `--hx-` prefixed tokens. No hardcoded colors, spacing, typography, or timing values. Check three-tier cascade (primitive → semantic → component). Verify dark mode token overrides work.\n\n2. **Accessibility (A11Y)** — WCAG 2.1 AA compliance. Verify ARIA roles, states, properties. Keyboard navigation (arrow keys, Enter, Space, Home, End). Focus management and focus-ring visibility. Screen reader announcements. Reduced-motion support.\n\n3. **Functionality** — Test all public properties, methods, events. Edge cases (empty state, overflow, rapid toggling). Slot behavior (default + named slots). Reactive property updates. Event bubbling/composition through Shadow DOM.\n\n4. **TypeScript** — Strict mode compliance. No `any` types. Proper type exports. ElementInternals usage if form-associated. Decorator usage (@customElement, @property, @state, @query).\n\n5. **CSS/Styling** — Shadow DOM encapsulation verified. CSS Parts exposed and documented. No style leakage. Responsive behavior. CSS containment where appropriate. Host styles properly scoped.\n\n6. **CEM Accuracy** — Custom Elements Manifest matches actual public API. All properties, events, slots, CSS parts, CSS custom properties documented with descriptions. Run `npm run cem` and diff.\n\n7. **Tests** — Test file exists and covers: rendering, property reflection, event emission, keyboard interaction, accessibility (aXe), slot projection, edge cases. Coverage target 80%+.\n\n8. **Storybook** — Stories exist for all variants. Controls wired to all public properties. Autodocs working from CEM. Visual regression baseline exists.\n\n9. **Drupal Compatibility** — Component works in Twig templates without modification. No JavaScript framework dependencies. Progressive enhancement friendly. Server-side rendering considerations.\n\n10. **Portability** — Works without build tools (CDN usage). No external dependencies beyond Lit. Lazy-loadable. Tree-shakeable.\n\n11. **wc-mcp Health Score** — No baseline score available yet. Target: 100 (A). Document all issues found.\n\n### Deliverable\nCreate a detailed markdown report as a comment in the PR documenting ALL findings across every category. Categorize issues as: CRITICAL (blocks release), HIGH (must fix), MEDIUM (should fix), LOW (nice to have). Fix any CRITICAL or HIGH issues directly. For MEDIUM/LOW, document them clearly for follow-up tickets.\n\n### Files to examine\n- `hx-accordion.ts` — main component\n- `hx-accordion.styles.ts` — styles\n- `hx-accordion.test.ts` — tests\n- `hx-accordion.stories.ts` — stories\n- `index.ts` — re-exports\n- Any sub-component files (hx-accordion-item)",
  "title": "Deep Audit v2: hx-accordion",
  "status": "backlog",
  "branchName": "feature/deep-audit-v2-hx-accordion",
  "complexity": "architectural",
  "priority": 3,
  "source": "api",
  "trustTier": 1,
  "quarantineStatus": "passed",
  "quarantineId": "72d9babb-0dc0-45ca-bbd8-1bb39bb36198",
  "id": "feature-1772817611085-stfqce2yg",
  "descriptionHistory": [
    {
      "description": "## Deep Component Audit — hx-accordion\n\n**Component directory:** `packages/hx-library/src/components/hx-accordion/`\n**Sub-components:** hx-accordion-item (lives in same directory)\n\n### Audit Scope (ALL areas — leave nothing unchecked)\n\n1. **Design Tokens** — Verify ALL CSS custom properties use `--hx-` prefixed tokens. No hardcoded colors, spacing, typography, or timing values. Check three-tier cascade (primitive → semantic → component). Verify dark mode token overrides work.\n\n2. **Accessibility (A11Y)** — WCAG 2.1 AA compliance. Verify ARIA roles, states, properties. Keyboard navigation (arrow keys, Enter, Space, Home, End). Focus management and focus-ring visibility. Screen reader announcements. Reduced-motion support.\n\n3. **Functionality** — Test all public properties, methods, events. Edge cases (empty state, overflow, rapid toggling). Slot behavior (default + named slots). Reactive property updates. Event bubbling/composition through Shadow DOM.\n\n4. **TypeScript** — Strict mode compliance. No `any` types. Proper type exports. ElementInternals usage if form-associated. Decorator usage (@customElement, @property, @state, @query).\n\n5. **CSS/Styling** — Shadow DOM encapsulation verified. CSS Parts exposed and documented. No style leakage. Responsive behavior. CSS containment where appropriate. Host styles properly scoped.\n\n6. **CEM Accuracy** — Custom Elements Manifest matches actual public API. All properties, events, slots, CSS parts, CSS custom properties documented with descriptions. Run `npm run cem` and diff.\n\n7. **Tests** — Test file exists and covers: rendering, property reflection, event emission, keyboard interaction, accessibility (aXe), slot projection, edge cases. Coverage target 80%+.\n\n8. **Storybook** — Stories exist for all variants. Controls wired to all public properties. Autodocs working from CEM. Visual regression baseline exists.\n\n9. **Drupal Compatibility** — Component works in Twig templates without modification. No JavaScript framework dependencies. Progressive enhancement friendly. Server-side rendering considerations.\n\n10. **Portability** — Works without build tools (CDN usage). No external dependencies beyond Lit. Lazy-loadable. Tree-shakeable.\n\n11. **wc-mcp Health Score** — No baseline score available yet. Target: 100 (A). Document all issues found.\n\n### Deliverable\nCreate a detailed markdown report as a comment in the PR documenting ALL findings across every category. Categorize issues as: CRITICAL (blocks release), HIGH (must fix), MEDIUM (should fix), LOW (nice to have). Fix any CRITICAL or HIGH issues directly. For MEDIUM/LOW, document them clearly for follow-up tickets.\n\n### Files to examine\n- `hx-accordion.ts` — main component\n- `hx-accordion.styles.ts` — styles\n- `hx-accordion.test.ts` — tests\n- `hx-accordion.stories.ts` — stories\n- `index.ts` — re-exports\n- Any sub-component files (hx-accordion-item)",
      "timestamp": "2026-03-06T17:20:11.085Z",
      "source": "initial"
    }
  ],
  "createdAt": "2026-03-06T17:20:11.085Z",
  "statusHistory": [
    {
      "from": null,
      "to": "backlog",
      "timestamp": "2026-03-06T17:20:11.085Z",
      "reason": "Feature created"
    }
  ]
}